raydl/__init__.py
raydl/__main__.py
raydl/collect_env.py
raydl/image.py
raydl/initialization.py
raydl/sfdb.py
raydl/tensor.py
raydl/time.py
raydl/utils.py
raydl-0.0.10.dist-info/LICENSE
raydl-0.0.10.dist-info/METADATA
raydl-0.0.10.dist-info/WHEEL
raydl-0.0.10.dist-info/top_level.txt
raydl-0.0.10.dist-info/RECORD
