Metadata-Version: 2.1
Name: raydl
Version: 0.0.10
Summary: The library of utilities to help you deal with the deep learning in PyTorch.
Author: Ray Wang
License: MIT License
Project-URL: Homepage, https://github.com/budui/raydl
Keywords: PyTorch,torch,deep learning,machine learning,ml,neural network
Classifier: License :: OSI Approved :: MIT License
Classifier: Programming Language :: Python :: 3
Requires-Python: >=3.9
License-File: LICENSE
Requires-Dist: torch
Provides-Extra: dev
Requires-Dist: black ; extra == 'dev'
Requires-Dist: ruff ; extra == 'dev'
Requires-Dist: isort ; extra == 'dev'
Requires-Dist: pytest ; extra == 'dev'
